printp/__init__.py
printp/cli.py
printp/pprint_custom.py
printp/printp.py
printp-0.1.4.dist-info/entry_points.txt
printp-0.1.4.dist-info/WHEEL
printp-0.1.4.dist-info/METADATA
printp-0.1.4.dist-info/RECORD
